{"id":"20865349-65ef-4cf2-b6ab-5ed226de2417","urn":147848,"ukprn":10086701,"name":"Outwood Academy Riverside","establishmentType":35,"establishmentGroup":11,"establishmentStatus":1,"establishmentPhase":4,"address":{"addressLine1":"100 Russell Street","addressLine2":"Middlehaven","town":"Middlesbrough","county":"North Yorkshire","postcode":"TS1 2AD"},"location":{"latitude":54.5747623,"longitude":-1.227435,"regionCode":"E12000001","localAuthorityCode":"806","districtAdministrativeCode":"E06000002","administrativeWardCode":"E05009857","parliamentaryConstituencyCode":"E14000819","msoaCode":"E02002496","lsoaCode":"E01035190"},"contact":{"telephone":"01642549950"},"minAge":11,"maxAge":16,"gender":3,"boarders":1,"officialSixthForm":2,"nurseryProvision":2,"religiousCharacter":6,"admissionsPolicy":4,"schoolCapacity":1050,"totalPupils":219,"totalBoys":109,"totalGirls":110,"specialClasses":0,"percentageFreeSchoolMeals":58.9,"trustSchool":3,"trustCode":4119,"schoolSponsorCode":4118,"urbanRural":"C1","head":{"title":"Mrs","firstName":"Melissa","lastName":"Brant-Smith"},"createdAt":"2024-03-28T11:47:15.884Z","updatedAt":"2023-09-06T13:14:34.833Z","type":"school","privateBetaSchool":true}
