{"id":"3b0eaa78-7bcd-4de8-8d14-8e49ff5e471e","urn":137121,"ukprn":10034922,"name":"Harris Academy Beckenham","establishmentType":28,"establishmentGroup":10,"establishmentStatus":1,"establishmentPhase":4,"address":{"addressLine1":"Manor Way","town":"Beckenham","county":"Kent","postcode":"BR3 3SJ"},"location":{"latitude":51.4005012,"longitude":-0.0267839,"regionCode":"E12000007","localAuthorityCode":"305","districtAdministrativeCode":"E09000006","administrativeWardCode":"E05013999","parliamentaryConstituencyCode":"E14000551","msoaCode":"E02000138","lsoaCode":"E01000770"},"contact":{"website":"http://www.harrisbeckenham.org.uk/","telephone":"02086508694"},"minAge":11,"maxAge":18,"gender":3,"boarders":1,"officialSixthForm":1,"nurseryProvision":0,"religiousCharacter":6,"admissionsPolicy":4,"schoolCapacity":1200,"totalPupils":1135,"totalBoys":733,"totalGirls":402,"specialClasses":2,"percentageFreeSchoolMeals":19.1,"trustSchool":3,"trustCode":3320,"schoolSponsorCode":3319,"furtherEducationType":0,"urbanRural":"A1","head":{"title":"Mrs","firstName":"Ciara","lastName":"Warnock","jobTitle":"Executive Principal"},"ofsted":{"rating":1,"lastInspectionDate":"2017-06-06T23:00:00.000Z"},"createdAt":"2024-03-28T11:05:43.691Z","updatedAt":"2023-09-06T13:14:34.833Z"}