{"id":"61f776a0-e646-4ab0-b24a-ad6bae432287","urn":137352,"ukprn":10035022,"name":"Shelley College, A Share Academy","establishmentType":34,"establishmentGroup":10,"establishmentStatus":1,"establishmentPhase":4,"address":{"addressLine1":"Huddersfield Road","addressLine2":"Shelley","town":"Huddersfield","county":"West Yorkshire","postcode":"HD8 8NL"},"location":{"latitude":53.5918544,"longitude":-1.6660489,"regionCode":"E12000003","localAuthorityCode":"382","districtAdministrativeCode":"E08000034","administrativeWardCode":"E05008562","parliamentaryConstituencyCode":"E14000666","msoaCode":"E02002326","lsoaCode":"E01011118"},"contact":{"website":"http://home.shelleycollege.org/","telephone":"01484868773"},"minAge":13,"maxAge":18,"gender":3,"boarders":1,"officialSixthForm":1,"nurseryProvision":0,"childcareFacilities":0,"religiousCharacter":0,"admissionsPolicy":4,"schoolCapacity":1319,"totalPupils":1358,"totalBoys":731,"totalGirls":627,"specialClasses":2,"percentageFreeSchoolMeals":13,"trustSchool":3,"trustCode":5635,"schoolSponsorCode":5574,"furtherEducationType":0,"urbanRural":"F1","head":{"title":"Mr","firstName":"David","lastName":"Wadsworth","jobTitle":"Principal"},"ofsted":{"rating":1,"lastInspectionDate":"2013-05-15T23:00:00.000Z"},"createdAt":"2024-03-28T11:47:15.834Z","updatedAt":"2023-09-06T13:14:34.833Z","type":"school","privateBetaSchool":true}
