{"id":"81e49b4f-1d39-4bcb-be6a-5a8684147d81","urn":138103,"ukprn":10037105,"name":"Southmoor Academy","establishmentType":34,"establishmentGroup":10,"establishmentStatus":1,"establishmentPhase":4,"address":{"addressLine1":"Ryhope Road","town":"Sunderland","county":"Tyne and Wear","postcode":"SR2 7TF"},"location":{"latitude":54.8900304,"longitude":-1.3763024,"regionCode":"E12000001","localAuthorityCode":"394","districtAdministrativeCode":"E08000024","administrativeWardCode":"E05001167","parliamentaryConstituencyCode":"E14000982","msoaCode":"E02001812","lsoaCode":"E01008740"},"contact":{"website":"http://www.southmoorschool.co.uk/","telephone":"01915949991"},"minAge":11,"maxAge":18,"gender":3,"boarders":1,"officialSixthForm":1,"nurseryProvision":2,"childcareFacilities":0,"religiousCharacter":0,"admissionsPolicy":4,"schoolCapacity":1264,"totalPupils":1440,"totalBoys":707,"totalGirls":733,"specialClasses":2,"percentageFreeSchoolMeals":29.7,"trustSchool":3,"trustCode":5712,"schoolSponsorCode":4599,"furtherEducationType":0,"urbanRural":"A1","head":{"title":"Mrs","firstName":"Joanne","lastName":"Maw","jobTitle":"Principal"},"ofsted":{"rating":2,"lastInspectionDate":"2022-09-27T23:00:00.000Z"},"createdAt":"2024-03-28T11:05:43.472Z","updatedAt":"2023-09-06T13:14:34.833Z"}