{"id":"a33126d4-4659-4d2e-bf4a-b276c2177c10","urn":142425,"ukprn":10054649,"name":"Freehold Community Academy","establishmentType":34,"establishmentGroup":10,"establishmentStatus":1,"establishmentPhase":2,"address":{"addressLine1":"Sidmouth Street","town":"Oldham","county":"Greater Manchester","postcode":"OL9 7RG"},"location":{"latitude":53.53590209999999,"longitude":-2.1370349,"regionCode":"E12000002","localAuthorityCode":"353","districtAdministrativeCode":"E08000004","administrativeWardCode":"E05014665","parliamentaryConstituencyCode":"E14000871","msoaCode":"E02007000","lsoaCode":"E01005460"},"contact":{"website":"www.freeholdprimaryacademy.co.uk","telephone":"01617705725"},"minAge":3,"maxAge":11,"gender":3,"boarders":1,"officialSixthForm":2,"nurseryProvision":1,"childcareFacilities":0,"religiousCharacter":0,"admissionsPolicy":0,"schoolCapacity":420,"totalPupils":486,"totalBoys":243,"totalGirls":243,"specialClasses":2,"percentageFreeSchoolMeals":32.8,"trustSchool":3,"trustCode":3112,"schoolSponsorCode":3113,"furtherEducationType":0,"urbanRural":"A1","head":{"title":"Mrs","firstName":"Nicola","lastName":"Maher","jobTitle":"Principal"},"ofsted":{"rating":2,"lastInspectionDate":"2018-09-25T23:00:00.000Z"},"createdAt":"2024-03-28T11:47:15.906Z","updatedAt":"2023-09-06T13:14:34.833Z","type":"school"}